aliyunsdksls/__init__.py
aliyunsdksls/endpoint.py
aliyunsdksls/request/__init__.py
aliyunsdksls/request/v20191023/AnalyzeAppLogRequest.py
aliyunsdksls/request/v20191023/AnalyzeProductLogRequest.py
aliyunsdksls/request/v20191023/CreateAppRequest.py
aliyunsdksls/request/v20191023/DataExpressionProcessRequest.py
aliyunsdksls/request/v20191023/DeleteAppRequest.py
aliyunsdksls/request/v20191023/DescribeAppRequest.py
aliyunsdksls/request/v20191023/DisableAlertRequest.py
aliyunsdksls/request/v20191023/EnableAlertRequest.py
aliyunsdksls/request/v20191023/GetAlertHistoriesRequest.py
aliyunsdksls/request/v20191023/GetAlertRequest.py
aliyunsdksls/request/v20191023/GetSlsServiceRequest.py
aliyunsdksls/request/v20191023/InitProjectAlertResourceRequest.py
aliyunsdksls/request/v20191023/InitUserAlertResourceRequest.py
aliyunsdksls/request/v20191023/OpenSlsServiceRequest.py
aliyunsdksls/request/v20191023/SetAlertActionPolicyRequest.py
aliyunsdksls/request/v20191023/SetAlertCenterResourceRequest.py
aliyunsdksls/request/v20191023/SyncAlertGroupsRequest.py
aliyunsdksls/request/v20191023/SyncAlertUsersRequest.py
aliyunsdksls/request/v20191023/UpdateAppRequest.py
aliyunsdksls/request/v20191023/__init__.py
aliyun_python_sdk_sls-1.1.2.dist-info/LICENSE
aliyun_python_sdk_sls-1.1.2.dist-info/METADATA
aliyun_python_sdk_sls-1.1.2.dist-info/WHEEL
aliyun_python_sdk_sls-1.1.2.dist-info/top_level.txt
aliyun_python_sdk_sls-1.1.2.dist-info/RECORD
